odoo/addons/account_invoice_date_due/README.rst
odoo/addons/account_invoice_date_due/__init__.py
odoo/addons/account_invoice_date_due/__manifest__.py
odoo/addons/account_invoice_date_due/i18n/account_invoice_date_due.pot
odoo/addons/account_invoice_date_due/i18n/ca.po
odoo/addons/account_invoice_date_due/i18n/de.po
odoo/addons/account_invoice_date_due/i18n/es.po
odoo/addons/account_invoice_date_due/i18n/fr.po
odoo/addons/account_invoice_date_due/i18n/fr_FR.po
odoo/addons/account_invoice_date_due/i18n/it.po
odoo/addons/account_invoice_date_due/models/__init__.py
odoo/addons/account_invoice_date_due/models/account_move.py
odoo/addons/account_invoice_date_due/readme/CONFIGURE.md
odoo/addons/account_invoice_date_due/readme/CONTRIBUTORS.md
odoo/addons/account_invoice_date_due/readme/DESCRIPTION.md
odoo/addons/account_invoice_date_due/readme/USAGE.md
odoo/addons/account_invoice_date_due/security/security.xml
odoo/addons/account_invoice_date_due/static/description/icon.png
odoo/addons/account_invoice_date_due/static/description/index.html
odoo/addons/account_invoice_date_due/tests/__init__.py
odoo/addons/account_invoice_date_due/tests/test_account_invoice_date_due.py
odoo/addons/account_invoice_date_due/views/account_move_date_due.xml
odoo_addon_account_invoice_date_due-18.0.1.0.1.dist-info/METADATA
odoo_addon_account_invoice_date_due-18.0.1.0.1.dist-info/WHEEL
odoo_addon_account_invoice_date_due-18.0.1.0.1.dist-info/top_level.txt
odoo_addon_account_invoice_date_due-18.0.1.0.1.dist-info/RECORD
